Workbook

Sheet Cover
A1: Sales Analytics Workbook
A2: Price, profitability, and promotion-elasticity dashboards based on all 1,000 daily observations.
A5: Sheet | B5: Purpose
A6: Dashboard | B6: Executive summary with KPIs, promotion elasticity, and monthly trend charts.
A7: Daily Metrics | B7: Daily sales price per unit, average unit sales price, and daily demand trend.
A8: Profitability | B8: Daily and monthly gross profit %, gross profit per unit %, and margin trend diagnostics.
A9: Promotion Analysis | B9: Three selected promotion/special periods with baseline comparisons and elasticity.
A10: SALES_EDA | B10: Source data and live calculated metric columns.

Sheet SALES_EDA
A1: Date | B1: Sales | C1: cost_of_sales | D1: quantity_sold | E1: year | F1: month_number | G1: month_name | H1: year_month | I1: day_of_month | J1: day_of_week | K1: day_name | L1: day_type | M1: price_per_unit | N1: cost_per_unit | O1: gross_profit | P1: gross_profit_percent | Q1: gross_profit_per_unit | R1: gross_profit_per_unit_percent | S1: average_unit_sales_price | T1: rolling_average_price
A2: 41638.083 | B2: 223937.97 | C2: 230079.62 | D2: 6827 | E2: 2013 | F2: 12 | G2: Dec | H2: 41609 | I2: 30 | J2: 2 | K2: Mon | L2: Weekday | M2: =IFERROR(B2/D2,0) -> 32.801812 | N2: =IFERROR(C2/D2,0) -> 33.701424 | O2: =B2-C2 -> -6141.6531 | P2: =IFERROR(O2/B2,0) -> -0.027425689 | Q2: =M2-N2 -> -0.8996123 | R2: =IFERROR(Q2/M2,0) -> -0.027425689 | S2: =IFERROR(SUM($B$2:$B$1001)/SUM($D$2:$D$1001),0) -> 35.267973 | T2: =AVERAGEIFS($M$2:$M$1001,$A$2:$A$1001,">="&A2-29,$A$2:$A$1001,"<="&A2) -> 32.801812
A3: 41639.083 | B3: 300345.48 | C3: 306986.12 | D3: 9268 | E3: 2013 | F3: 12 | G3: Dec | H3: 41609 | I3: 31 | J3: 3 | K3: Tue | L3: Weekday | M3: =IFERROR(B3/D3,0) -> 32.40672 | N3: =IFERROR(C3/D3,0) -> 33.123233 | O3: =B3-C3 -> -6640.6359 | P3: =IFERROR(O3/B3,0) -> -0.022109991 | Q3: =M3-N3 -> -0.71651229 | R3: =IFERROR(Q3/M3,0) -> -0.022109991 | S3: =IFERROR(SUM($B$2:$B$1001)/SUM($D$2:$D$1001),0) -> 35.267973 | T3: =AVERAGEIFS($M$2:$M$1001,$A$2:$A$1001,">="&A3-29,$A$2:$A$1001,"<="&A3) -> 32.604266
A4: 41640.083 | B4: 86782.468 | C4: 87986.318 | D4: 2678 | E4: 2014 | F4: 1 | G4: Jan | H4: 41640 | I4: 1 | J4: 4 | K4: Wed | L4: Weekday | M4: =IFERROR(B4/D4,0) -> 32.405701 | N4: =IFERROR(C4/D4,0) -> 32.855235 | O4: =B4-C4 -> -1203.8505 | P4: =IFERROR(O4/B4,0) -> -0.013872047 | Q4: =M4-N4 -> -0.44953342 | R4: =IFERROR(Q4/M4,0) -> -0.013872047 | S4: =IFERROR(SUM($B$2:$B$1001)/SUM($D$2:$D$1001),0) -> 35.267973 | T4: =AVERAGEIFS($M$2:$M$1001,$A$2:$A$1001,">="&A4-29,$A$2:$A$1001,"<="&A4) -> 32.538078
A5: 41641.083 | B5: 200173.12 | C5: 202881.18 | D5: 6175 | E5: 2014 | F5: 1 | G5: Jan | H5: 41640 | I5: 2 | J5: 5 | K5: Thu | L5: Weekday | M5: =IFERROR(B5/D5,0) -> 32.416699 | N5: =IFERROR(C5/D5,0) -> 32.855251 | O5: =B5-C5 -> -2708.061 | P5: =IFERROR(O5/B5,0) -> -0.013528595 | Q5: =M5-N5 -> -0.43855238 | R5: =IFERROR(Q5/M5,0) -> -0.013528595 | S5: =IFERROR(SUM($B$2:$B$1001)/SUM($D$2:$D$1001),0) -> 35.267973 | T5: =AVERAGEIFS($M$2:$M$1001,$A$2:$A$1001,">="&A5-29,$A$2:$A$1001,"<="&A5) -> 32.507733
A6: 41642.083 | B6: 326906.07 | C6: 333806.29 | D6: 10084 | E6: 2014 | F6: 1 | G6: Jan | H6: 41640 | I6: 3 | J6: 6 | K6: Fri | L6: Weekday | M6: =IFERROR(B6/D6,0) -> 32.418294 | N6: =IFERROR(C6/D6,0) -> 33.102568 | O6: =B6-C6 -> -6900.2177 | P6: =IFERROR(O6/B6,0) -> -0.021107646 | Q6: =M6-N6 -> -0.68427387 | R6: =IFERROR(Q6/M6,0) -> -0.021107646 | S6: =IFERROR(SUM($B$2:$B$1001)/SUM($D$2:$D$1001),0) -> 35.267973 | T6: =AVERAGEIFS($M$2:$M$1001,$A$2:$A$1001,">="&A6-29,$A$2:$A$1001,"<="&A6) -> 32.489845
A7: 41643.083 | B7: 307043.94 | C7: 313652.35 | D7: 9470 | E7: 2014 | F7: 1 | G7: Jan | H7: 41640 | I7: 4 | J7: 7 | K7: Sat | L7: Weekday | M7: =IFERROR(B7/D7,0) -> 32.422802 | N7: =IFERROR(C7/D7,0) -> 33.120628 | O7: =B7-C7 -> -6608.4129 | P7: =IFERROR(O7/B7,0) -> -0.021522695 | Q7: =M7-N7 -> -0.69782607 | R7: =IFERROR(Q7/M7,0) -> -0.021522695 | S7: =IFERROR(SUM($B$2:$B$1001)/SUM($D$2:$D$1001),0) -> 35.267973 | T7: =AVERAGEIFS($M$2:$M$1001,$A$2:$A$1001,">="&A7-29,$A$2:$A$1001,"<="&A7) -> 32.478671
A8: 41644.083 | B8: 179188.88 | C8: 183083.28 | D8: 5524 | E8: 2014 | F8: 1 | G8: Jan | H8: 41640 | I8: 5 | J8: 1 | K8: Sun | L8: Weekday | M8: =IFERROR(B8/D8,0) -> 32.438248 | N8: =IFERROR(C8/D8,0) -> 33.143245 | O8: =B8-C8 -> -3894.4005 | P8: =IFERROR(O8/B8,0) -> -0.021733494 | Q8: =M8-N8 -> -0.70499647 | R8: =IFERROR(Q8/M8,0) -> -0.021733494 | S8: =IFERROR(SUM($B$2:$B$1001)/SUM($D$2:$D$1001),0) -> 35.267973 | T8: =AVERAGEIFS($M$2:$M$1001,$A$2:$A$1001,">="&A8-29,$A$2:$A$1001,"<="&A8) -> 32.472897
A9: 41645.083 | B9: 306351.95 | C9: 313446.07 | D9: 9448 | E9: 2014 | F9: 1 | G9: Jan | H9: 41640 | I9: 6 | J9: 2 | K9: Mon | L9: Weekday | M9: =IFERROR(B9/D9,0) -> 32.425058 | N9: =IFERROR(C9/D9,0) -> 33.175917 | O9: =B9-C9 -> -7094.1173 | P9: =IFERROR(O9/B9,0) -> -0.023156756 | Q9: =M9-N9 -> -0.75085915 | R9: =IFERROR(Q9/M9,0) -> -0.023156756 | S9: =IFERROR(SUM($B$2:$B$1001)/SUM($D$2:$D$1001),0) -> 35.267973 | T9: =AVERAGEIFS($M$2:$M$1001,$A$2:$A$1001,">="&A9-29,$A$2:$A$1001,"<="&A9) -> 32.466917
A10: 41646.083 | B10: 224020.41 | C10: 229533.97 | D10: 6911 | E10: 2014 | F10: 1 | G10: Jan | H10: 41640 | I10: 7 | J10: 3 | K10: Tue | L10: Weekday | M10: =IFERROR(B10/D10,0) -> 32.41505 | N10: =IFERROR(C10/D10,0) -> 33.212845 | O10: =B10-C10 -> -5513.5638 | P10: =IFERROR(O10/B10,0) -> -0.024611881 | Q10: =M10-N10 -> -0.79779536 | R10: =IFERROR(Q10/M10,0) -> -0.024611881 | S10: =IFERROR(SUM($B$2:$B$1001)/SUM($D$2:$D$1001),0) -> 35.267973 | T10: =AVERAGEIFS($M$2:$M$1001,$A$2:$A$1001,">="&A10-29,$A$2:$A$1001,"<="&A10) -> 32.461154
A11: 41647.083 | B11: 101836.4 | C11: 99381.968 | D11: 2990 | E11: 2014 | F11: 1 | G11: Jan | H11: 41640 | I11: 8 | J11: 4 | K11: Wed | L11: Weekday | M11: =IFERROR(B11/D11,0) -> 34.058997 | N11: =IFERROR(C11/D11,0) -> 33.238116 | O11: =B11-C11 -> 2454.4347 | P11: =IFERROR(O11/B11,0) -> 0.024101742 | Q11: =M11-N11 -> 0.82088118 | R11: =IFERROR(Q11/M11,0) -> 0.024101742 | S11: =IFERROR(SUM($B$2:$B$1001)/SUM($D$2:$D$1001),0) -> 35.267973 | T11: =AVERAGEIFS($M$2:$M$1001,$A$2:$A$1001,">="&A11-29,$A$2:$A$1001,"<="&A11) -> 32.620938
A12: 41648.083 | B12: 107804.3 | C12: 104816.46 | D12: 3159 | E12: 2014 | F12: 1 | G12: Jan | H12: 41640 | I12: 9 | J12: 5 | K12: Thu | L12: Weekday | M12: =IFERROR(B12/D12,0) -> 34.126086 | N12: =IFERROR(C12/D12,0) -> 33.180265 | O12: =B12-C12 -> 2987.8464 | P12: =IFERROR(O12/B12,0) -> 0.027715465 | Q12: =M12-N12 -> 0.94582033 | R12: =IFERROR(Q12/M12,0) -> 0.027715465 | S12: =IFERROR(SUM($B$2:$B$1001)/SUM($D$2:$D$1001),0) -> 35.267973 | T12: =AVERAGEIFS($M$2:$M$1001,$A$2:$A$1001,">="&A12-29,$A$2:$A$1001,"<="&A12) -> 32.75777
A13: 41649.083 | B13: 144829.96 | C13: 141334 | D13: 4246 | E13: 2014 | F13: 1 | G13: Jan | H13: 41640 | I13: 10 | J13: 6 | K13: Fri | L13: Weekday | M13: =IFERROR(B13/D13,0) -> 34.10974 | N13: =IFERROR(C13/D13,0) -> 33.286386 | O13: =B13-C13 -> 3495.9604 | P13: =IFERROR(O13/B13,0) -> 0.024138379 | Q13: =M13-N13 -> 0.82335385 | R13: =IFERROR(Q13/M13,0) -> 0.024138379 | S13: =IFERROR(SUM($B$2:$B$1001)/SUM($D$2:$D$1001),0) -> 35.267973 | T13: =AVERAGEIFS($M$2:$M$1001,$A$2:$A$1001,">="&A13-29,$A$2:$A$1001,"<="&A13) -> 32.870434
... A1001: 42637.083 | B1001: 151639.18 | C1001: 135498.16 | D1001: 3758 | E1001: 2016 | F1001: 9 | G1001: Sep | H1001: 42614 | I1001: 24 | J1001: 7 | K1001: Sat | L1001: Weekday | M1001: =IFERROR(B1001/D1001,0) -> 40.351033 | N1001: =IFERROR(C1001/D1001,0) -> 36.055924 | O1001: =B1001-C1001 -> 16141.021 | P1001: =IFERROR(O1001/B1001,0) -> 0.1064436 | Q1001: =M1001-N1001 -> 4.2951093 | R1001: =IFERROR(Q1001/M1001,0) -> 0.1064436 | S1001: =IFERROR(SUM($B$2:$B$1001)/SUM($D$2:$D$1001),0) -> 35.267973 | T1001: =AVERAGEIFS($M$2:$M$1001,$A$2:$A$1001,">="&A1001-29,$A$2:$A$1001,"<="&A1001) -> 37.978896

Sheet Dashboard
A1: Sales Price, Profit & Promotion Elasticity Dashboard
A2: Daily unit-price, gross-profit, and demand-response metrics from 1,000 sales days: 2013-12-30 to 2016-09-24.
A4: Story in brief: The product shows very elastic demand during discount windows: every selected promotion has elasticity below -10, meaning volume rose far more than price fell. Gross margin recovered strongly by 2016 as selling price moved above cost per unit, but deep discounts still require careful margin monitoring. The dashboard separates price, sales, margin, and elasticity so promotion decisions can balance demand lift against profit quality.
A8: TOTAL SALES | D8: TOTAL UNITS | G8: AVG UNIT SALES PRICE | J8: TOTAL GROSS PROFIT %
A9: =SUM(SALES_EDA!$B$2:$B$1001) -> 1.8225914e+08 | D9: =SUM(SALES_EDA!$D$2:$D$1001) -> 5167837 | G9: =SUM(SALES_EDA!$B$2:$B$1001)/SUM(SALES_EDA!$D$2:$D$1001) -> 35.267973 | J9: =SUM(SALES_EDA!$O$2:$O$1001)/SUM(SALES_EDA!$B$2:$B$1001) -> -0.041107107
A12: PROMOTION / SPECIAL PERIODS — ELASTICITY OF DEMAND
A14: Period | B14: Start | C14: End | D14: Days | E14: Promo Avg Price | F14: Baseline Avg Price | G14: Price Change % | H14: Promo Avg Units | I14: Baseline Avg Units | J14: Quantity Change % | K14: Elasticity
A15: Extended low-price special | B15: 41768 | C15: 41918 | D15: =C15-B15+1 -> 151 | E15: =AVERAGEIFS(SALES_EDA!$M$2:$M$1001,SALES_EDA!$A$2:$A$1001,">="&B15,SALES_EDA!$A$2:$A$1001,"<"&C15+1) -> 33.064252 | F15: =(SUMIFS(SALES_EDA!$M$2:$M$1001,SALES_EDA!$A$2:$A$1001,">="&B15-14,SALES_EDA!$A$2:$A$1001,"<"&B15)+SUMIFS(SALES_EDA!$M$2:$M$1001,SALES_EDA!$A$2:$A$1001,">="&C15+1,SALES_EDA!$A$2:$A$1001,"<"&C15+15))/(COUNTIFS(SALES_EDA!$A$2:$A$1001,">="&B15-14,SALES_EDA!$A$2:$A$1001,"<"&B15)+COUNTIFS(SALES_EDA!$A$2:$A$1001,">="&C15+1,SALES_EDA!$A$2:$A$1001,"<"&C15+15)) -> 35.932205 | G15: =E15/F15-1 -> -0.079815672 | H15: =AVERAGEIFS(SALES_EDA!$D$2:$D$1001,SALES_EDA!$A$2:$A$1001,">="&B15,SALES_EDA!$A$2:$A$1001,"<"&C15+1) -> 7892.6026 | I15: =(SUMIFS(SALES_EDA!$D$2:$D$1001,SALES_EDA!$A$2:$A$1001,">="&B15-14,SALES_EDA!$A$2:$A$1001,"<"&B15)+SUMIFS(SALES_EDA!$D$2:$D$1001,SALES_EDA!$A$2:$A$1001,">="&C15+1,SALES_EDA!$A$2:$A$1001,"<"&C15+15))/(COUNTIFS(SALES_EDA!$A$2:$A$1001,">="&B15-14,SALES_EDA!$A$2:$A$1001,"<"&B15)+COUNTIFS(SALES_EDA!$A$2:$A$1001,">="&C15+1,SALES_EDA!$A$2:$A$1001,"<"&C15+15)) -> 3596.7143 | J15: =H15/I15-1 -> 1.1943924 | K15: =J15/G15 -> -14.964385
A16: Autumn deep discount | B16: 42270 | C16: 42283 | D16: =C16-B16+1 -> 14 | E16: =AVERAGEIFS(SALES_EDA!$M$2:$M$1001,SALES_EDA!$A$2:$A$1001,">="&B16,SALES_EDA!$A$2:$A$1001,"<"&C16+1) -> 33.396349 | F16: =(SUMIFS(SALES_EDA!$M$2:$M$1001,SALES_EDA!$A$2:$A$1001,">="&B16-14,SALES_EDA!$A$2:$A$1001,"<"&B16)+SUMIFS(SALES_EDA!$M$2:$M$1001,SALES_EDA!$A$2:$A$1001,">="&C16+1,SALES_EDA!$A$2:$A$1001,"<"&C16+15))/(COUNTIFS(SALES_EDA!$A$2:$A$1001,">="&B16-14,SALES_EDA!$A$2:$A$1001,"<"&B16)+COUNTIFS(SALES_EDA!$A$2:$A$1001,">="&C16+1,SALES_EDA!$A$2:$A$1001,"<"&C16+15)) -> 39.282415 | G16: =E16/F16-1 -> -0.14983971 | H16: =AVERAGEIFS(SALES_EDA!$D$2:$D$1001,SALES_EDA!$A$2:$A$1001,">="&B16,SALES_EDA!$A$2:$A$1001,"<"&C16+1) -> 8089.3571 | I16: =(SUMIFS(SALES_EDA!$D$2:$D$1001,SALES_EDA!$A$2:$A$1001,">="&B16-14,SALES_EDA!$A$2:$A$1001,"<"&B16)+SUMIFS(SALES_EDA!$D$2:$D$1001,SALES_EDA!$A$2:$A$1001,">="&C16+1,SALES_EDA!$A$2:$A$1001,"<"&C16+15))/(COUNTIFS(SALES_EDA!$A$2:$A$1001,">="&B16-14,SALES_EDA!$A$2:$A$1001,"<"&B16)+COUNTIFS(SALES_EDA!$A$2:$A$1001,">="&C16+1,SALES_EDA!$A$2:$A$1001,"<"&C16+15)) -> 1575.7857 | J16: =H16/I16-1 -> 4.1335388 | K16: =J16/G16 -> -27.586404
A17: Early-2016 deep discount | B17: 42391 | C17: 42408 | D17: =C17-B17+1 -> 18 | E17: =AVERAGEIFS(SALES_EDA!$M$2:$M$1001,SALES_EDA!$A$2:$A$1001,">="&B17,SALES_EDA!$A$2:$A$1001,"<"&C17+1) -> 34.072824 | F17: =(SUMIFS(SALES_EDA!$M$2:$M$1001,SALES_EDA!$A$2:$A$1001,">="&B17-14,SALES_EDA!$A$2:$A$1001,"<"&B17)+SUMIFS(SALES_EDA!$M$2:$M$1001,SALES_EDA!$A$2:$A$1001,">="&C17+1,SALES_EDA!$A$2:$A$1001,"<"&C17+15))/(COUNTIFS(SALES_EDA!$A$2:$A$1001,">="&B17-14,SALES_EDA!$A$2:$A$1001,"<"&B17)+COUNTIFS(SALES_EDA!$A$2:$A$1001,">="&C17+1,SALES_EDA!$A$2:$A$1001,"<"&C17+15)) -> 40.769814 | G17: =E17/F17-1 -> -0.16426344 | H17: =AVERAGEIFS(SALES_EDA!$D$2:$D$1001,SALES_EDA!$A$2:$A$1001,">="&B17,SALES_EDA!$A$2:$A$1001,"<"&C17+1) -> 7925.1111 | I17: =(SUMIFS(SALES_EDA!$D$2:$D$1001,SALES_EDA!$A$2:$A$1001,">="&B17-14,SALES_EDA!$A$2:$A$1001,"<"&B17)+SUMIFS(SALES_EDA!$D$2:$D$1001,SALES_EDA!$A$2:$A$1001,">="&C17+1,SALES_EDA!$A$2:$A$1001,"<"&C17+15))/(COUNTIFS(SALES_EDA!$A$2:$A$1001,">="&B17-14,SALES_EDA!$A$2:$A$1001,"<"&B17)+COUNTIFS(SALES_EDA!$A$2:$A$1001,">="&C17+1,SALES_EDA!$A$2:$A$1001,"<"&C17+15)) -> 2898.6071 | J17: =H17/I17-1 -> 1.7341101 | K17: =J17/G17 -> -10.556884
A53: MONTHLY TREND DATA
A54: Month | B54: Sales | C54: Units | D54: Avg Price | E54: Gross Profit % | F54: Days
A55: 41609 | B55: =SUMIFS(SALES_EDA!$B$2:$B$1001,SALES_EDA!$A$2:$A$1001,">="&A55,SALES_EDA!$A$2:$A$1001,"<"&EDATE(A55,1)) -> 524283.45 | C55: =SUMIFS(SALES_EDA!$D$2:$D$1001,SALES_EDA!$A$2:$A$1001,">="&A55,SALES_EDA!$A$2:$A$1001,"<"&EDATE(A55,1)) -> 16095 | D55: =IFERROR(B55/C55,0) -> 32.574306 | E55: =IFERROR(SUMIFS(SALES_EDA!$O$2:$O$1001,SALES_EDA!$A$2:$A$1001,">="&A55,SALES_EDA!$A$2:$A$1001,"<"&EDATE(A55,1))/B55,0) -> -0.024380493 | F55: =COUNTIFS(SALES_EDA!$A$2:$A$1001,">="&A55,SALES_EDA!$A$2:$A$1001,"<"&EDATE(A55,1)) -> 2
A56: 41640 | B56: =SUMIFS(SALES_EDA!$B$2:$B$1001,SALES_EDA!$A$2:$A$1001,">="&A56,SALES_EDA!$A$2:$A$1001,"<"&EDATE(A56,1)) -> 4008180.5 | C56: =SUMIFS(SALES_EDA!$D$2:$D$1001,SALES_EDA!$A$2:$A$1001,">="&A56,SALES_EDA!$A$2:$A$1001,"<"&EDATE(A56,1)) -> 119965 | D56: =IFERROR(B56/C56,0) -> 33.411249 | E56: =IFERROR(SUMIFS(SALES_EDA!$O$2:$O$1001,SALES_EDA!$A$2:$A$1001,">="&A56,SALES_EDA!$A$2:$A$1001,"<"&EDATE(A56,1))/B56,0) -> 0.0031088035 | F56: =COUNTIFS(SALES_EDA!$A$2:$A$1001,">="&A56,SALES_EDA!$A$2:$A$1001,"<"&EDATE(A56,1)) -> 31
A57: 41671 | B57: =SUMIFS(SALES_EDA!$B$2:$B$1001,SALES_EDA!$A$2:$A$1001,">="&A57,SALES_EDA!$A$2:$A$1001,"<"&EDATE(A57,1)) -> 5780487.2 | C57: =SUMIFS(SALES_EDA!$D$2:$D$1001,SALES_EDA!$A$2:$A$1001,">="&A57,SALES_EDA!$A$2:$A$1001,"<"&EDATE(A57,1)) -> 178035 | D57: =IFERROR(B57/C57,0) -> 32.468263 | E57: =IFERROR(SUMIFS(SALES_EDA!$O$2:$O$1001,SALES_EDA!$A$2:$A$1001,">="&A57,SALES_EDA!$A$2:$A$1001,"<"&EDATE(A57,1))/B57,0) -> -0.023006951 | F57: =COUNTIFS(SALES_EDA!$A$2:$A$1001,">="&A57,SALES_EDA!$A$2:$A$1001,"<"&EDATE(A57,1)) -> 28
A58: 41699 | B58: =SUMIFS(SALES_EDA!$B$2:$B$1001,SALES_EDA!$A$2:$A$1001,">="&A58,SALES_EDA!$A$2:$A$1001,"<"&EDATE(A58,1)) -> 8279517.2 | C58: =SUMIFS(SALES_EDA!$D$2:$D$1001,SALES_EDA!$A$2:$A$1001,">="&A58,SALES_EDA!$A$2:$A$1001,"<"&EDATE(A58,1)) -> 252836 | D58: =IFERROR(B58/C58,0) -> 32.746591 | E58: =IFERROR(SUMIFS(SALES_EDA!$O$2:$O$1001,SALES_EDA!$A$2:$A$1001,">="&A58,SALES_EDA!$A$2:$A$1001,"<"&EDATE(A58,1))/B58,0) -> -0.016442607 | F58: =COUNTIFS(SALES_EDA!$A$2:$A$1001,">="&A58,SALES_EDA!$A$2:$A$1001,"<"&EDATE(A58,1)) -> 31
A59: 41730 | B59: =SUMIFS(SALES_EDA!$B$2:$B$1001,SALES_EDA!$A$2:$A$1001,">="&A59,SALES_EDA!$A$2:$A$1001,"<"&EDATE(A59,1)) -> 6435743.3 | C59: =SUMIFS(SALES_EDA!$D$2:$D$1001,SALES_EDA!$A$2:$A$1001,">="&A59,SALES_EDA!$A$2:$A$1001,"<"&EDATE(A59,1)) -> 190091 | D59: =IFERROR(B59/C59,0) -> 33.856118 | E59: =IFERROR(SUMIFS(SALES_EDA!$O$2:$O$1001,SALES_EDA!$A$2:$A$1001,">="&A59,SALES_EDA!$A$2:$A$1001,"<"&EDATE(A59,1))/B59,0) -> -0.0068213335 | F59: =COUNTIFS(SALES_EDA!$A$2:$A$1001,">="&A59,SALES_EDA!$A$2:$A$1001,"<"&EDATE(A59,1)) -> 30
A60: 41760 | B60: =SUMIFS(SALES_EDA!$B$2:$B$1001,SALES_EDA!$A$2:$A$1001,">="&A60,SALES_EDA!$A$2:$A$1001,"<"&EDATE(A60,1)) -> 7694906.2 | C60: =SUMIFS(SALES_EDA!$D$2:$D$1001,SALES_EDA!$A$2:$A$1001,">="&A60,SALES_EDA!$A$2:$A$1001,"<"&EDATE(A60,1)) -> 235793 | D60: =IFERROR(B60/C60,0) -> 32.634159 | E60: =IFERROR(SUMIFS(SALES_EDA!$O$2:$O$1001,SALES_EDA!$A$2:$A$1001,">="&A60,SALES_EDA!$A$2:$A$1001,"<"&EDATE(A60,1))/B60,0) -> -0.041889304 | F60: =COUNTIFS(SALES_EDA!$A$2:$A$1001,">="&A60,SALES_EDA!$A$2:$A$1001,"<"&EDATE(A60,1)) -> 31
A61: 41791 | B61: =SUMIFS(SALES_EDA!$B$2:$B$1001,SALES_EDA!$A$2:$A$1001,">="&A61,SALES_EDA!$A$2:$A$1001,"<"&EDATE(A61,1)) -> 6456943.6 | C61: =SUMIFS(SALES_EDA!$D$2:$D$1001,SALES_EDA!$A$2:$A$1001,">="&A61,SALES_EDA!$A$2:$A$1001,"<"&EDATE(A61,1)) -> 198857 | D61: =IFERROR(B61/C61,0) -> 32.470286 | E61: =IFERROR(SUMIFS(SALES_EDA!$O$2:$O$1001,SALES_EDA!$A$2:$A$1001,">="&A61,SALES_EDA!$A$2:$A$1001,"<"&EDATE(A61,1))/B61,0) -> -0.029255329 | F61: =COUNTIFS(SALES_EDA!$A$2:$A$1001,">="&A61,SALES_EDA!$A$2:$A$1001,"<"&EDATE(A61,1)) -> 30
A62: 41821 | B62: =SUMIFS(SALES_EDA!$B$2:$B$1001,SALES_EDA!$A$2:$A$1001,">="&A62,SALES_EDA!$A$2:$A$1001,"<"&EDATE(A62,1)) -> 4933710.8 | C62: =SUMIFS(SALES_EDA!$D$2:$D$1001,SALES_EDA!$A$2:$A$1001,">="&A62,SALES_EDA!$A$2:$A$1001,"<"&EDATE(A62,1)) -> 147449 | D62: =IFERROR(B62/C62,0) -> 33.460456 | E62: =IFERROR(SUMIFS(SALES_EDA!$O$2:$O$1001,SALES_EDA!$A$2:$A$1001,">="&A62,SALES_EDA!$A$2:$A$1001,"<"&EDATE(A62,1))/B62,0) -> -0.014428106 | F62: =COUNTIFS(SALES_EDA!$A$2:$A$1001,">="&A62,SALES_EDA!$A$2:$A$1001,"<"&EDATE(A62,1)) -> 31
A63: 41852 | B63: =SUMIFS(SALES_EDA!$B$2:$B$1001,SALES_EDA!$A$2:$A$1001,">="&A63,SALES_EDA!$A$2:$A$1001,"<"&EDATE(A63,1)) -> 10010378 | C63: =SUMIFS(SALES_EDA!$D$2:$D$1001,SALES_EDA!$A$2:$A$1001,">="&A63,SALES_EDA!$A$2:$A$1001,"<"&EDATE(A63,1)) -> 310572 | D63: =IFERROR(B63/C63,0) -> 32.232069 | E63: =IFERROR(SUMIFS(SALES_EDA!$O$2:$O$1001,SALES_EDA!$A$2:$A$1001,">="&A63,SALES_EDA!$A$2:$A$1001,"<"&EDATE(A63,1))/B63,0) -> -0.051352119 | F63: =COUNTIFS(SALES_EDA!$A$2:$A$1001,">="&A63,SALES_EDA!$A$2:$A$1001,"<"&EDATE(A63,1)) -> 31
A64: 41883 | B64: =SUMIFS(SALES_EDA!$B$2:$B$1001,SALES_EDA!$A$2:$A$1001,">="&A64,SALES_EDA!$A$2:$A$1001,"<"&EDATE(A64,1)) -> 7643452.7 | C64: =SUMIFS(SALES_EDA!$D$2:$D$1001,SALES_EDA!$A$2:$A$1001,">="&A64,SALES_EDA!$A$2:$A$1001,"<"&EDATE(A64,1)) -> 237742 | D64: =IFERROR(B64/C64,0) -> 32.150199 | E64: =IFERROR(SUMIFS(SALES_EDA!$O$2:$O$1001,SALES_EDA!$A$2:$A$1001,">="&A64,SALES_EDA!$A$2:$A$1001,"<"&EDATE(A64,1))/B64,0) -> -0.071971055 | F64: =COUNTIFS(SALES_EDA!$A$2:$A$1001,">="&A64,SALES_EDA!$A$2:$A$1001,"<"&EDATE(A64,1)) -> 30
A65: 41913 | B65: =SUMIFS(SALES_EDA!$B$2:$B$1001,SALES_EDA!$A$2:$A$1001,">="&A65,SALES_EDA!$A$2:$A$1001,"<"&EDATE(A65,1)) -> 5924683.4 | C65: =SUMIFS(SALES_EDA!$D$2:$D$1001,SALES_EDA!$A$2:$A$1001,">="&A65,SALES_EDA!$A$2:$A$1001,"<"&EDATE(A65,1)) -> 171709 | D65: =IFERROR(B65/C65,0) -> 34.50421 | E65: =IFERROR(SUMIFS(SALES_EDA!$O$2:$O$1001,SALES_EDA!$A$2:$A$1001,">="&A65,SALES_EDA!$A$2:$A$1001,"<"&EDATE(A65,1))/B65,0) -> -0.019204053 | F65: =COUNTIFS(SALES_EDA!$A$2:$A$1001,">="&A65,SALES_EDA!$A$2:$A$1001,"<"&EDATE(A65,1)) -> 31
A66: 41944 | B66: =SUMIFS(SALES_EDA!$B$2:$B$1001,SALES_EDA!$A$2:$A$1001,">="&A66,SALES_EDA!$A$2:$A$1001,"<"&EDATE(A66,1)) -> 2631353.3 | C66: =SUMIFS(SALES_EDA!$D$2:$D$1001,SALES_EDA!$A$2:$A$1001,">="&A66,SALES_EDA!$A$2:$A$1001,"<"&EDATE(A66,1)) -> 68569 | D66: =IFERROR(B66/C66,0) -> 38.375262 | E66: =IFERROR(SUMIFS(SALES_EDA!$O$2:$O$1001,SALES_EDA!$A$2:$A$1001,">="&A66,SALES_EDA!$A$2:$A$1001,"<"&EDATE(A66,1))/B66,0) -> 0.043410554 | F66: =COUNTIFS(SALES_EDA!$A$2:$A$1001,">="&A66,SALES_EDA!$A$2:$A$1001,"<"&EDATE(A66,1)) -> 30
... A88: 42614 | B88: =SUMIFS(SALES_EDA!$B$2:$B$1001,SALES_EDA!$A$2:$A$1001,">="&A88,SALES_EDA!$A$2:$A$1001,"<"&EDATE(A88,1)) -> 2789053.8 | C88: =SUMIFS(SALES_EDA!$D$2:$D$1001,SALES_EDA!$A$2:$A$1001,">="&A88,SALES_EDA!$A$2:$A$1001,"<"&EDATE(A88,1)) -> 76411 | D88: =IFERROR(B88/C88,0) -> 36.500684 | E88: =IFERROR(SUMIFS(SALES_EDA!$O$2:$O$1001,SALES_EDA!$A$2:$A$1001,">="&A88,SALES_EDA!$A$2:$A$1001,"<"&EDATE(A88,1))/B88,0) -> 0.0071706049 | F88: =COUNTIFS(SALES_EDA!$A$2:$A$1001,">="&A88,SALES_EDA!$A$2:$A$1001,"<"&EDATE(A88,1)) -> 24

Sheet Daily Metrics
A1: Daily Price & Demand Dashboard
A2: Answers: daily sales price per unit and weighted average unit sales price.
A4: Story in brief: Daily unit sales price is calculated as Sales divided by quantity sold for every transaction day. The workbook-level weighted average unit sales price is R35.27, which is lower than the simple average daily price because high-volume discount periods pull the weighted result down. This view helps compare daily price movement against volume response.
A8: WEIGHTED AVG UNIT PRICE | D8: SIMPLE AVG DAILY PRICE | G8: TOTAL UNITS SOLD
A9: =SUM(SALES_EDA!$B$2:$B$1001)/SUM(SALES_EDA!$D$2:$D$1001) -> 35.267973 | D9: =AVERAGE(SALES_EDA!$M$2:$M$1001) -> 36.827322 | G9: =SUM(SALES_EDA!$D$2:$D$1001) -> 5167837
A13: DAILY PRICE SAMPLE & CHART DATA
A14: Date | B14: Daily Sales Price / Unit | C14: Rolling Avg Price | D14: Quantity Sold | E14: Sales
A15: =SALES_EDA!A2 -> 41638.083 | B15: =SALES_EDA!M2 -> 32.801812 | C15: =SALES_EDA!T2 -> 32.801812 | D15: =SALES_EDA!D2 -> 6827 | E15: =SALES_EDA!B2 -> 223937.97
A16: =SALES_EDA!A3 -> 41639.083 | B16: =SALES_EDA!M3 -> 32.40672 | C16: =SALES_EDA!T3 -> 32.604266 | D16: =SALES_EDA!D3 -> 9268 | E16: =SALES_EDA!B3 -> 300345.48
A17: =SALES_EDA!A4 -> 41640.083 | B17: =SALES_EDA!M4 -> 32.405701 | C17: =SALES_EDA!T4 -> 32.538078 | D17: =SALES_EDA!D4 -> 2678 | E17: =SALES_EDA!B4 -> 86782.468
A18: =SALES_EDA!A5 -> 41641.083 | B18: =SALES_EDA!M5 -> 32.416699 | C18: =SALES_EDA!T5 -> 32.507733 | D18: =SALES_EDA!D5 -> 6175 | E18: =SALES_EDA!B5 -> 200173.12
A19: =SALES_EDA!A6 -> 41642.083 | B19: =SALES_EDA!M6 -> 32.418294 | C19: =SALES_EDA!T6 -> 32.489845 | D19: =SALES_EDA!D6 -> 10084 | E19: =SALES_EDA!B6 -> 326906.07
A20: =SALES_EDA!A7 -> 41643.083 | B20: =SALES_EDA!M7 -> 32.422802 | C20: =SALES_EDA!T7 -> 32.478671 | D20: =SALES_EDA!D7 -> 9470 | E20: =SALES_EDA!B7 -> 307043.94
A21: =SALES_EDA!A8 -> 41644.083 | B21: =SALES_EDA!M8 -> 32.438248 | C21: =SALES_EDA!T8 -> 32.472897 | D21: =SALES_EDA!D8 -> 5524 | E21: =SALES_EDA!B8 -> 179188.88
A22: =SALES_EDA!A9 -> 41645.083 | B22: =SALES_EDA!M9 -> 32.425058 | C22: =SALES_EDA!T9 -> 32.466917 | D22: =SALES_EDA!D9 -> 9448 | E22: =SALES_EDA!B9 -> 306351.95
A23: =SALES_EDA!A10 -> 41646.083 | B23: =SALES_EDA!M10 -> 32.41505 | C23: =SALES_EDA!T10 -> 32.461154 | D23: =SALES_EDA!D10 -> 6911 | E23: =SALES_EDA!B10 -> 224020.41
A24: =SALES_EDA!A11 -> 41647.083 | B24: =SALES_EDA!M11 -> 34.058997 | C24: =SALES_EDA!T11 -> 32.620938 | D24: =SALES_EDA!D11 -> 2990 | E24: =SALES_EDA!B11 -> 101836.4
A25: =SALES_EDA!A12 -> 41648.083 | B25: =SALES_EDA!M12 -> 34.126086 | C25: =SALES_EDA!T12 -> 32.75777 | D25: =SALES_EDA!D12 -> 3159 | E25: =SALES_EDA!B12 -> 107804.3
A26: =SALES_EDA!A13 -> 41649.083 | B26: =SALES_EDA!M13 -> 34.10974 | C26: =SALES_EDA!T13 -> 32.870434 | D26: =SALES_EDA!D13 -> 4246 | E26: =SALES_EDA!B13 -> 144829.96
... A1014: =SALES_EDA!A1001 -> 42637.083 | B1014: =SALES_EDA!M1001 -> 40.351033 | C1014: =SALES_EDA!T1001 -> 37.978896 | D1014: =SALES_EDA!D1001 -> 3758 | E1014: =SALES_EDA!B1001 -> 151639.18

Sheet Profitability
A1: Profitability Dashboard
A2: Answers: daily gross profit %, daily gross profit per unit %, and margin direction.
A4: Story in brief: Gross profit % is Sales less cost of sales divided by Sales. Gross profit per unit % measures the unit margin against the daily selling price. Margins start negative in early periods and improve materially by 2016 as sales price rises above cost per unit.
A8: TOTAL GROSS PROFIT % | D8: AVG GROSS PROFIT / UNIT | G8: LATEST DAILY GP %
A9: =SUM(SALES_EDA!$O$2:$O$1001)/SUM(SALES_EDA!$B$2:$B$1001) -> -0.041107107 | D9: =AVERAGE(SALES_EDA!$Q$2:$Q$1001) -> -0.37382741 | G9: =SALES_EDA!P1001 -> 0.1064436
A13: MONTHLY PROFITABILITY DATA
A14: Month | B14: Sales | C14: Gross Profit | D14: Gross Profit % | E14: Gross Profit / Unit %
A15: 41609 | B15: =SUMIFS(SALES_EDA!$B$2:$B$1001,SALES_EDA!$A$2:$A$1001,">="&A15,SALES_EDA!$A$2:$A$1001,"<"&EDATE(A15,1)) -> 524283.45 | C15: =SUMIFS(SALES_EDA!$O$2:$O$1001,SALES_EDA!$A$2:$A$1001,">="&A15,SALES_EDA!$A$2:$A$1001,"<"&EDATE(A15,1)) -> -12782.289 | D15: =IFERROR(C15/B15,0) -> -0.024380493 | E15: =AVERAGEIFS(SALES_EDA!$R$2:$R$1001,SALES_EDA!$A$2:$A$1001,">="&A15,SALES_EDA!$A$2:$A$1001,"<"&EDATE(A15,1)) -> -0.02476784
A16: 41640 | B16: =SUMIFS(SALES_EDA!$B$2:$B$1001,SALES_EDA!$A$2:$A$1001,">="&A16,SALES_EDA!$A$2:$A$1001,"<"&EDATE(A16,1)) -> 4008180.5 | C16: =SUMIFS(SALES_EDA!$O$2:$O$1001,SALES_EDA!$A$2:$A$1001,">="&A16,SALES_EDA!$A$2:$A$1001,"<"&EDATE(A16,1)) -> 12460.645 | D16: =IFERROR(C16/B16,0) -> 0.0031088035 | E16: =AVERAGEIFS(SALES_EDA!$R$2:$R$1001,SALES_EDA!$A$2:$A$1001,">="&A16,SALES_EDA!$A$2:$A$1001,"<"&EDATE(A16,1)) -> 0.010110119
A17: 41671 | B17: =SUMIFS(SALES_EDA!$B$2:$B$1001,SALES_EDA!$A$2:$A$1001,">="&A17,SALES_EDA!$A$2:$A$1001,"<"&EDATE(A17,1)) -> 5780487.2 | C17: =SUMIFS(SALES_EDA!$O$2:$O$1001,SALES_EDA!$A$2:$A$1001,">="&A17,SALES_EDA!$A$2:$A$1001,"<"&EDATE(A17,1)) -> -132991.39 | D17: =IFERROR(C17/B17,0) -> -0.023006951 | E17: =AVERAGEIFS(SALES_EDA!$R$2:$R$1001,SALES_EDA!$A$2:$A$1001,">="&A17,SALES_EDA!$A$2:$A$1001,"<"&EDATE(A17,1)) -> -0.015519653
A18: 41699 | B18: =SUMIFS(SALES_EDA!$B$2:$B$1001,SALES_EDA!$A$2:$A$1001,">="&A18,SALES_EDA!$A$2:$A$1001,"<"&EDATE(A18,1)) -> 8279517.2 | C18: =SUMIFS(SALES_EDA!$O$2:$O$1001,SALES_EDA!$A$2:$A$1001,">="&A18,SALES_EDA!$A$2:$A$1001,"<"&EDATE(A18,1)) -> -136136.84 | D18: =IFERROR(C18/B18,0) -> -0.016442607 | E18: =AVERAGEIFS(SALES_EDA!$R$2:$R$1001,SALES_EDA!$A$2:$A$1001,">="&A18,SALES_EDA!$A$2:$A$1001,"<"&EDATE(A18,1)) -> -0.0032285624
A19: 41730 | B19: =SUMIFS(SALES_EDA!$B$2:$B$1001,SALES_EDA!$A$2:$A$1001,">="&A19,SALES_EDA!$A$2:$A$1001,"<"&EDATE(A19,1)) -> 6435743.3 | C19: =SUMIFS(SALES_EDA!$O$2:$O$1001,SALES_EDA!$A$2:$A$1001,">="&A19,SALES_EDA!$A$2:$A$1001,"<"&EDATE(A19,1)) -> -43900.351 | D19: =IFERROR(C19/B19,0) -> -0.0068213335 | E19: =AVERAGEIFS(SALES_EDA!$R$2:$R$1001,SALES_EDA!$A$2:$A$1001,">="&A19,SALES_EDA!$A$2:$A$1001,"<"&EDATE(A19,1)) -> -0.00061283744
A20: 41760 | B20: =SUMIFS(SALES_EDA!$B$2:$B$1001,SALES_EDA!$A$2:$A$1001,">="&A20,SALES_EDA!$A$2:$A$1001,"<"&EDATE(A20,1)) -> 7694906.2 | C20: =SUMIFS(SALES_EDA!$O$2:$O$1001,SALES_EDA!$A$2:$A$1001,">="&A20,SALES_EDA!$A$2:$A$1001,"<"&EDATE(A20,1)) -> -322334.26 | D20: =IFERROR(C20/B20,0) -> -0.041889304 | E20: =AVERAGEIFS(SALES_EDA!$R$2:$R$1001,SALES_EDA!$A$2:$A$1001,">="&A20,SALES_EDA!$A$2:$A$1001,"<"&EDATE(A20,1)) -> -0.0329521
A21: 41791 | B21: =SUMIFS(SALES_EDA!$B$2:$B$1001,SALES_EDA!$A$2:$A$1001,">="&A21,SALES_EDA!$A$2:$A$1001,"<"&EDATE(A21,1)) -> 6456943.6 | C21: =SUMIFS(SALES_EDA!$O$2:$O$1001,SALES_EDA!$A$2:$A$1001,">="&A21,SALES_EDA!$A$2:$A$1001,"<"&EDATE(A21,1)) -> -188900.01 | D21: =IFERROR(C21/B21,0) -> -0.029255329 | E21: =AVERAGEIFS(SALES_EDA!$R$2:$R$1001,SALES_EDA!$A$2:$A$1001,">="&A21,SALES_EDA!$A$2:$A$1001,"<"&EDATE(A21,1)) -> -0.017892064
A22: 41821 | B22: =SUMIFS(SALES_EDA!$B$2:$B$1001,SALES_EDA!$A$2:$A$1001,">="&A22,SALES_EDA!$A$2:$A$1001,"<"&EDATE(A22,1)) -> 4933710.8 | C22: =SUMIFS(SALES_EDA!$O$2:$O$1001,SALES_EDA!$A$2:$A$1001,">="&A22,SALES_EDA!$A$2:$A$1001,"<"&EDATE(A22,1)) -> -71184.101 | D22: =IFERROR(C22/B22,0) -> -0.014428106 | E22: =AVERAGEIFS(SALES_EDA!$R$2:$R$1001,SALES_EDA!$A$2:$A$1001,">="&A22,SALES_EDA!$A$2:$A$1001,"<"&EDATE(A22,1)) -> 0.0041082198
A23: 41852 | B23: =SUMIFS(SALES_EDA!$B$2:$B$1001,SALES_EDA!$A$2:$A$1001,">="&A23,SALES_EDA!$A$2:$A$1001,"<"&EDATE(A23,1)) -> 10010378 | C23: =SUMIFS(SALES_EDA!$O$2:$O$1001,SALES_EDA!$A$2:$A$1001,">="&A23,SALES_EDA!$A$2:$A$1001,"<"&EDATE(A23,1)) -> -514054.14 | D23: =IFERROR(C23/B23,0) -> -0.051352119 | E23: =AVERAGEIFS(SALES_EDA!$R$2:$R$1001,SALES_EDA!$A$2:$A$1001,">="&A23,SALES_EDA!$A$2:$A$1001,"<"&EDATE(A23,1)) -> -0.043119807
A24: 41883 | B24: =SUMIFS(SALES_EDA!$B$2:$B$1001,SALES_EDA!$A$2:$A$1001,">="&A24,SALES_EDA!$A$2:$A$1001,"<"&EDATE(A24,1)) -> 7643452.7 | C24: =SUMIFS(SALES_EDA!$O$2:$O$1001,SALES_EDA!$A$2:$A$1001,">="&A24,SALES_EDA!$A$2:$A$1001,"<"&EDATE(A24,1)) -> -550107.35 | D24: =IFERROR(C24/B24,0) -> -0.071971055 | E24: =AVERAGEIFS(SALES_EDA!$R$2:$R$1001,SALES_EDA!$A$2:$A$1001,">="&A24,SALES_EDA!$A$2:$A$1001,"<"&EDATE(A24,1)) -> -0.038749998
A25: 41913 | B25: =SUMIFS(SALES_EDA!$B$2:$B$1001,SALES_EDA!$A$2:$A$1001,">="&A25,SALES_EDA!$A$2:$A$1001,"<"&EDATE(A25,1)) -> 5924683.4 | C25: =SUMIFS(SALES_EDA!$O$2:$O$1001,SALES_EDA!$A$2:$A$1001,">="&A25,SALES_EDA!$A$2:$A$1001,"<"&EDATE(A25,1)) -> -113777.94 | D25: =IFERROR(C25/B25,0) -> -0.019204053 | E25: =AVERAGEIFS(SALES_EDA!$R$2:$R$1001,SALES_EDA!$A$2:$A$1001,">="&A25,SALES_EDA!$A$2:$A$1001,"<"&EDATE(A25,1)) -> 0.014312271
A26: 41944 | B26: =SUMIFS(SALES_EDA!$B$2:$B$1001,SALES_EDA!$A$2:$A$1001,">="&A26,SALES_EDA!$A$2:$A$1001,"<"&EDATE(A26,1)) -> 2631353.3 | C26: =SUMIFS(SALES_EDA!$O$2:$O$1001,SALES_EDA!$A$2:$A$1001,">="&A26,SALES_EDA!$A$2:$A$1001,"<"&EDATE(A26,1)) -> 114228.51 | D26: =IFERROR(C26/B26,0) -> 0.043410554 | E26: =AVERAGEIFS(SALES_EDA!$R$2:$R$1001,SALES_EDA!$A$2:$A$1001,">="&A26,SALES_EDA!$A$2:$A$1001,"<"&EDATE(A26,1)) -> 0.059540101
... A48: 42614 | B48: =SUMIFS(SALES_EDA!$B$2:$B$1001,SALES_EDA!$A$2:$A$1001,">="&A48,SALES_EDA!$A$2:$A$1001,"<"&EDATE(A48,1)) -> 2789053.8 | C48: =SUMIFS(SALES_EDA!$O$2:$O$1001,SALES_EDA!$A$2:$A$1001,">="&A48,SALES_EDA!$A$2:$A$1001,"<"&EDATE(A48,1)) -> 19999.203 | D48: =IFERROR(C48/B48,0) -> 0.0071706049 | E48: =AVERAGEIFS(SALES_EDA!$R$2:$R$1001,SALES_EDA!$A$2:$A$1001,">="&A48,SALES_EDA!$A$2:$A$1001,"<"&EDATE(A48,1)) -> 0.064546657

Sheet Promotion Analysis
A1: Promotion / Special Period Elasticity Dashboard
A2: Answers: three selected periods and their price elasticity of demand.
A4: Story in brief: The selected promotion periods are sustained below-price windows identified from the source data. Elasticity is calculated as % change in average quantity divided by % change in average price, using the 14 days before and 14 days after each promotion as the baseline. All three periods show elastic demand, with volume responding sharply to discounted pricing.
A8: PROMOTION ELASTICITY TABLE
A10: Period | B10: Start | C10: End | D10: Days | E10: Promo Avg Price | F10: Baseline Avg Price | G10: Price Change % | H10: Promo Avg Units | I10: Baseline Avg Units | J10: Quantity Change % | K10: Elasticity
A11: Extended low-price special | B11: 41768 | C11: 41918 | D11: =C11-B11+1 -> 151 | E11: =AVERAGEIFS(SALES_EDA!$M$2:$M$1001,SALES_EDA!$A$2:$A$1001,">="&B11,SALES_EDA!$A$2:$A$1001,"<"&C11+1) -> 33.064252 | F11: =(SUMIFS(SALES_EDA!$M$2:$M$1001,SALES_EDA!$A$2:$A$1001,">="&B11-14,SALES_EDA!$A$2:$A$1001,"<"&B11)+SUMIFS(SALES_EDA!$M$2:$M$1001,SALES_EDA!$A$2:$A$1001,">="&C11+1,SALES_EDA!$A$2:$A$1001,"<"&C11+15))/(COUNTIFS(SALES_EDA!$A$2:$A$1001,">="&B11-14,SALES_EDA!$A$2:$A$1001,"<"&B11)+COUNTIFS(SALES_EDA!$A$2:$A$1001,">="&C11+1,SALES_EDA!$A$2:$A$1001,"<"&C11+15)) -> 35.932205 | G11: =E11/F11-1 -> -0.079815672 | H11: =AVERAGEIFS(SALES_EDA!$D$2:$D$1001,SALES_EDA!$A$2:$A$1001,">="&B11,SALES_EDA!$A$2:$A$1001,"<"&C11+1) -> 7892.6026 | I11: =(SUMIFS(SALES_EDA!$D$2:$D$1001,SALES_EDA!$A$2:$A$1001,">="&B11-14,SALES_EDA!$A$2:$A$1001,"<"&B11)+SUMIFS(SALES_EDA!$D$2:$D$1001,SALES_EDA!$A$2:$A$1001,">="&C11+1,SALES_EDA!$A$2:$A$1001,"<"&C11+15))/(COUNTIFS(SALES_EDA!$A$2:$A$1001,">="&B11-14,SALES_EDA!$A$2:$A$1001,"<"&B11)+COUNTIFS(SALES_EDA!$A$2:$A$1001,">="&C11+1,SALES_EDA!$A$2:$A$1001,"<"&C11+15)) -> 3596.7143 | J11: =H11/I11-1 -> 1.1943924 | K11: =J11/G11 -> -14.964385
A12: Autumn deep discount | B12: 42270 | C12: 42283 | D12: =C12-B12+1 -> 14 | E12: =AVERAGEIFS(SALES_EDA!$M$2:$M$1001,SALES_EDA!$A$2:$A$1001,">="&B12,SALES_EDA!$A$2:$A$1001,"<"&C12+1) -> 33.396349 | F12: =(SUMIFS(SALES_EDA!$M$2:$M$1001,SALES_EDA!$A$2:$A$1001,">="&B12-14,SALES_EDA!$A$2:$A$1001,"<"&B12)+SUMIFS(SALES_EDA!$M$2:$M$1001,SALES_EDA!$A$2:$A$1001,">="&C12+1,SALES_EDA!$A$2:$A$1001,"<"&C12+15))/(COUNTIFS(SALES_EDA!$A$2:$A$1001,">="&B12-14,SALES_EDA!$A$2:$A$1001,"<"&B12)+COUNTIFS(SALES_EDA!$A$2:$A$1001,">="&C12+1,SALES_EDA!$A$2:$A$1001,"<"&C12+15)) -> 39.282415 | G12: =E12/F12-1 -> -0.14983971 | H12: =AVERAGEIFS(SALES_EDA!$D$2:$D$1001,SALES_EDA!$A$2:$A$1001,">="&B12,SALES_EDA!$A$2:$A$1001,"<"&C12+1) -> 8089.3571 | I12: =(SUMIFS(SALES_EDA!$D$2:$D$1001,SALES_EDA!$A$2:$A$1001,">="&B12-14,SALES_EDA!$A$2:$A$1001,"<"&B12)+SUMIFS(SALES_EDA!$D$2:$D$1001,SALES_EDA!$A$2:$A$1001,">="&C12+1,SALES_EDA!$A$2:$A$1001,"<"&C12+15))/(COUNTIFS(SALES_EDA!$A$2:$A$1001,">="&B12-14,SALES_EDA!$A$2:$A$1001,"<"&B12)+COUNTIFS(SALES_EDA!$A$2:$A$1001,">="&C12+1,SALES_EDA!$A$2:$A$1001,"<"&C12+15)) -> 1575.7857 | J12: =H12/I12-1 -> 4.1335388 | K12: =J12/G12 -> -27.586404
A13: Early-2016 deep discount | B13: 42391 | C13: 42408 | D13: =C13-B13+1 -> 18 | E13: =AVERAGEIFS(SALES_EDA!$M$2:$M$1001,SALES_EDA!$A$2:$A$1001,">="&B13,SALES_EDA!$A$2:$A$1001,"<"&C13+1) -> 34.072824 | F13: =(SUMIFS(SALES_EDA!$M$2:$M$1001,SALES_EDA!$A$2:$A$1001,">="&B13-14,SALES_EDA!$A$2:$A$1001,"<"&B13)+SUMIFS(SALES_EDA!$M$2:$M$1001,SALES_EDA!$A$2:$A$1001,">="&C13+1,SALES_EDA!$A$2:$A$1001,"<"&C13+15))/(COUNTIFS(SALES_EDA!$A$2:$A$1001,">="&B13-14,SALES_EDA!$A$2:$A$1001,"<"&B13)+COUNTIFS(SALES_EDA!$A$2:$A$1001,">="&C13+1,SALES_EDA!$A$2:$A$1001,"<"&C13+15)) -> 40.769814 | G13: =E13/F13-1 -> -0.16426344 | H13: =AVERAGEIFS(SALES_EDA!$D$2:$D$1001,SALES_EDA!$A$2:$A$1001,">="&B13,SALES_EDA!$A$2:$A$1001,"<"&C13+1) -> 7925.1111 | I13: =(SUMIFS(SALES_EDA!$D$2:$D$1001,SALES_EDA!$A$2:$A$1001,">="&B13-14,SALES_EDA!$A$2:$A$1001,"<"&B13)+SUMIFS(SALES_EDA!$D$2:$D$1001,SALES_EDA!$A$2:$A$1001,">="&C13+1,SALES_EDA!$A$2:$A$1001,"<"&C13+15))/(COUNTIFS(SALES_EDA!$A$2:$A$1001,">="&B13-14,SALES_EDA!$A$2:$A$1001,"<"&B13)+COUNTIFS(SALES_EDA!$A$2:$A$1001,">="&C13+1,SALES_EDA!$A$2:$A$1001,"<"&C13+15)) -> 2898.6071 | J13: =H13/I13-1 -> 1.7341101 | K13: =J13/G13 -> -10.556884
